[{
	"CategoryID": 1,
	"CategoryName": "Категория 1",
	"Description": "Описание категории 1",
	"Picture": "../src/Cat1.svg",
	"StatusId": 1,
	"ResponsibleId": 1,
	"ProductsAmount": 120,
	"ProductsMax": 150
},
{
	"CategoryID": 2,
	"CategoryName": "Категория 2",
	"Description": "Описание категории 2",
	"Picture": "../src/Cat1.svg",
	"StatusId": 2,
	"ResponsibleId": 2,
	"ProductsAmount": 124,
	"ProductsMax": 150
},
{
	"CategoryID": 3,
	"CategoryName": "Категория 3",
	"Description": "Описание категории 3",
	"Picture": "../src/Cat1.svg",
	"StatusId": 1,
	"ResponsibleId": 3,
	"ProductsAmount": 100,
	"ProductsMax": 150
},
{
	"CategoryID": 4,
	"CategoryName": "Категория 4",
	"Description": "Описание категории 4",
	"Picture": "../src/Cat1.svg",
	"StatusId": 1,
	"ResponsibleId": 4,
	"ProductsAmount": 180,
	"ProductsMax": 150
}
]